{
  "dropdown-list-item": {
    "container": {
      "padding": {
        "vertical": {
          "value": "{padding.1}",
          "type": "dimension",
          "description": "Vertical padding for menu item container (top and bottom)"
        },
        "horizontal": {
          "value": "{padding.2}",
          "type": "dimension",
          "description": "Horizontal padding for menu item container (left and right)"
        }
      },
      "gap": {
        "primary": {
          "value": "{gap.2}",
          "type": "dimension",
          "description": "Primary gap between checkbox/check indicator and content area"
        },
        "content": {
          "value": "{gap.1}",
          "type": "dimension",
          "description": "Gap between icon and text content within content area"
        }
      },
      "border-radius": {
        "value": "{border.radius.sm}",
        "type": "dimension",
        "description": "Border radius for menu item container"
      },
      "min-height": {
        "value": "{size.11}",
        "type": "dimension",
        "description": "Minimum height for menu item container (44px)"
      }
    },
    "content": {
      "gap": {
        "primary": {
          "value": "{gap.1}",
          "type": "dimension",
          "description": "Gap between leading icon and text/description stack"
        },
        "secondary": {
          "value": "{gap.0[5]}",
          "type": "dimension",
          "description": "Gap between label and description text (2px)"
        }
      }
    },
    "icon": {
      "size": {
        "primary": {
          "value": "{size.icon.xs}",
          "type": "dimension",
          "description": "Size for main action/leading icons (14px)"
        },
        "description": {
          "value": "{size.2[5]}",
          "type": "dimension",
          "description": "Size for description/supporting icons (10px)"
        },
        "group": {
          "value": "{size.3}",
          "type": "dimension",
          "description": "Size for group title icons (12px)"
        }
      },
      "color": {
        "default": {
          "value": "{color.icon.neutral.moderate.1}",
          "type": "color",
          "description": "Default icon color for enabled state"
        },
        "disabled": {
          "value": "{color.icon.neutral.subtle.2}",
          "type": "color",
          "description": "Icon color for disabled state"
        }
      }
    },
    "avatar": {
      "size": {
        "value": "{size.xs}",
        "type": "dimension",
        "description": "Avatar size for list items with avatar variant"
      }
    },
    "checkbox": {
      "size": {
        "value": "{checkbox.container.size.xs}",
        "type": "dimension",
        "description": "Checkbox size for multi-select menu items"
      },
      "border-radius": {
        "value": "{checkbox.container.border-radius.xs}",
        "type": "dimension",
        "description": "Checkbox border radius for multi-select items"
      },
      "background": {
        "unchecked": {
          "default": {
            "value": "{checkbox.background.unchecked.default}",
            "type": "color",
            "description": "Background color for unchecked checkbox in default state"
          },
          "hover": {
            "value": "{checkbox.background.unchecked.hover}",
            "type": "color",
            "description": "Background color for unchecked checkbox on hover"
          },
          "disabled": {
            "value": "{checkbox.background.unchecked.disabled}",
            "type": "color",
            "description": "Background color for unchecked checkbox when disabled"
          }
        },
        "checked": {
          "default": {
            "value": "{checkbox.background.checked.default}",
            "type": "color",
            "description": "Background color for checked checkbox in default state"
          },
          "hover": {
            "value": "{checkbox.background.checked.hover}",
            "type": "color",
            "description": "Background color for checked checkbox on hover"
          },
          "disabled": {
            "value": "{checkbox.background.checked.disabled}",
            "type": "color",
            "description": "Background color for checked checkbox when disabled"
          }
        }
      },
      "border": {
        "unchecked": {
          "default": {
            "value": "{checkbox.border.unchecked.default}",
            "type": "color",
            "description": "Border color for unchecked checkbox in default state"
          },
          "hover": {
            "value": "{checkbox.border.unchecked.hover}",
            "type": "color",
            "description": "Border color for unchecked checkbox on hover"
          },
          "disabled": {
            "value": "{checkbox.border.unchecked.disabled}",
            "type": "color",
            "description": "Border color for unchecked checkbox when disabled"
          }
        },
        "checked": {
          "default": {
            "value": "{checkbox.border.checked.default}",
            "type": "color",
            "description": "Border color for checked checkbox in default state"
          },
          "hover": {
            "value": "{checkbox.border.checked.hover}",
            "type": "color",
            "description": "Border color for checked checkbox on hover"
          },
          "disabled": {
            "value": "{checkbox.border.checked.disabled}",
            "type": "color",
            "description": "Border color for checked checkbox when disabled"
          }
        }
      }
    },
    "text": {
      "label": {
        "typography": {
          "value": "{font.body.regular.md}",
          "type": "typography",
          "description": "Primary label text style (13px, Regular, 18px line-height)"
        },
        "color": {
          "default": {
            "value": "{color.text.neutral.title.1}",
            "type": "color",
            "description": "Label text color in default/enabled state"
          },
          "disabled": {
            "value": "{color.text.neutral.subtitle.2}",
            "type": "color",
            "description": "Label text color in disabled state"
          }
        }
      },
      "description": {
        "typography": {
          "value": "{font.body.regular.xs}",
          "type": "typography",
          "description": "Supporting description text style (11px, Regular, 16px line-height)"
        },
        "color": {
          "default": {
            "value": "{color.text.neutral.moderate.1}",
            "type": "color",
            "description": "Description text color in default/enabled state"
          },
          "disabled": {
            "value": "{color.text.neutral.subtitle.2}",
            "type": "color",
            "description": "Description text color in disabled state"
          }
        }
      },
      "supporting": {
        "typography": {
          "value": "{font.body.regular.xs}",
          "type": "typography",
          "description": "Supporting information text style (11px, Regular, 16px line-height)"
        },
        "color": {
          "default": {
            "value": "{color.text.neutral.body.2}",
            "type": "color",
            "description": "Supporting text color in default state"
          },
          "disabled": {
            "value": "{color.text.neutral.subtitle.2}",
            "type": "color",
            "description": "Supporting text color in disabled state"
          }
        }
      }
    },
    "background": {
      "default": {
        "value": "{color.background.neutral.base}",
        "type": "color",
        "description": "Background color for menu item in default/rest state"
      },
      "hover": {
        "value": "{color.background.neutral.subtle.2}",
        "type": "color",
        "description": "Background color for menu item on hover (Gray 100)"
      },
      "selected": {
        "value": "{color.background.brand.subtle.1}",
        "type": "color",
        "description": "Background color for selected menu item (Blue 50)"
      },
      "disabled": {
        "value": "{color.background.neutral.inactive}",
        "type": "color",
        "description": "Background color for disabled menu item (Gray 50)"
      }
    },
    "group-title": {
      "padding": {
        "top": {
          "value": "{padding.2}",
          "type": "dimension",
          "description": "Top padding for group title container (8px)"
        },
        "right": {
          "value": "{padding.2[5]}",
          "type": "dimension",
          "description": "Right padding for group title container (10px)"
        },
        "bottom": {
          "value": "{padding.1}",
          "type": "dimension",
          "description": "Bottom padding for group title container (4px)"
        },
        "left": {
          "value": "{padding.2}",
          "type": "dimension",
          "description": "Left padding for group title container (8px)"
        }
      },
      "gap": {
        "value": "{gap.1}",
        "type": "dimension",
        "description": "Gap between icon and title text (4px)"
      },
      "text": {
        "typography": {
          "value": "{font.body.medium.xs}",
          "type": "typography",
          "description": "Group title text style (11px, Medium, 16px line-height)"
        },
        "color": {
          "value": "{color.text.neutral.subtitle.1}",
          "type": "color",
          "description": "Group title text color (Gray 400)"
        }
      },
      "background": {
        "value": "{color.background.neutral.subtle.1}",
        "type": "color",
        "description": "Group title background color (Gray 50)"
      }
    },
    "search": {
      "container": {
        "padding": {
          "value": "{padding.2}",
          "type": "dimension",
          "description": "Container padding around search input (8px)"
        },
        "gap": {
          "value": "{gap.1[5]}",
          "type": "dimension",
          "description": "Gap within search container (6px)"
        }
      },
      "input": {
        "height": {
          "value": "{size.7}",
          "type": "dimension",
          "description": "Search input height (28px)"
        },
        "padding": {
          "vertical": {
            "value": "{padding.1[5]}",
            "type": "dimension",
            "description": "Vertical padding for search input (6px)"
          },
          "horizontal": {
            "value": "{padding.2}",
            "type": "dimension",
            "description": "Horizontal padding for search input (8px)"
          }
        },
        "border": {
          "color": {
            "default": {
              "value": "{color.border.neutral.default}",
              "type": "color",
              "description": "Search input border color in default state (Gray 300)"
            },
            "focus": {
              "value": "{color.border.primary.default}",
              "type": "color",
              "description": "Search input border color on focus"
            }
          },
          "width": {
            "value": "{border.width.default}",
            "type": "dimension",
            "description": "Search input border width (1px)"
          }
        },
        "border-radius": {
          "value": "{border.radius.sm}",
          "type": "dimension",
          "description": "Search input border radius (4px)"
        },
        "background": {
          "value": "{color.background.neutral.base}",
          "type": "color",
          "description": "Search input background color (White)"
        },
        "gap": {
          "value": "{gap.2}",
          "type": "dimension",
          "description": "Gap between search icon and placeholder text (8px)"
        }
      },
      "icon": {
        "size": {
          "value": "{size.4}",
          "type": "dimension",
          "description": "Search icon size (16px)"
        },
        "color": {
          "value": "{color.icon.neutral.moderate.2}",
          "type": "color",
          "description": "Search icon color (Gray 500)"
        }
      },
      "placeholder": {
        "typography": {
          "value": "{font.body.regular.base}",
          "type": "typography",
          "description": "Search placeholder text style (14px, Regular, 20px line-height)"
        },
        "color": {
          "value": "{color.text.neutral.subtitle.2}",
          "type": "color",
          "description": "Search placeholder text color (Gray 500)"
        }
      },
      "filter-icon": {
        "size": {
          "value": "{size.icon.xs}",
          "type": "dimension",
          "description": "Filter icon size within search (14px)"
        },
        "gap": {
          "value": "{gap.1}",
          "type": "dimension",
          "description": "Gap between filter icons (4px)"
        }
      }
    },
    "divider": {
      "height": {
        "value": "{size.0[25]}",
        "type": "dimension",
        "description": "Divider height (1px)"
      },
      "color": {
        "value": "{color.border.neutral.default}",
        "type": "color",
        "description": "Divider color (Gray 300)"
      },
      "margin": {
        "vertical": {
          "value": "{padding.0}",
          "type": "dimension",
          "description": "Vertical margin for divider (0px)"
        }
      }
    },
    "custom": {
      "padding": {
        "vertical": {
          "value": "{padding.2}",
          "type": "dimension",
          "description": "Vertical padding for custom content (8px)"
        },
        "horizontal": {
          "value": "{padding.0}",
          "type": "dimension",
          "description": "Horizontal padding for custom content (0px)"
        }
      },
      "border-radius": {
        "value": "{border.radius.sm}",
        "type": "dimension",
        "description": "Border radius for custom content container"
      },
      "background": {
        "value": "{color.background.neutral.subtle.2}",
        "type": "color",
        "description": "Background color for custom content area (Gray 100)"
      }
    },
    "check-indicator": {
      "size": {
        "value": "{size.4}",
        "type": "dimension",
        "description": "Check indicator icon size for selected single-select items (16px)"
      },
      "color": {
        "default": {
          "value": "{color.border.brand.default}",
          "type": "color",
          "description": "Check indicator color for selected items (Brand Blue)"
        }
      }
    },
    "tag": {
      "gap": {
        "value": "{gap.1}",
        "type": "dimension",
        "description": "Gap between multiple tags in badge container (4px)"
      }
    },
    "right-info": {
      "gap": {
        "value": "{gap.1}",
        "type": "dimension",
        "description": "Gap between right-aligned info elements like badges and icons (4px)"
      }
    },
    "keyboard-shortcut": {
      "typography": {
        "value": "{font.body.regular.xs}",
        "type": "typography",
        "description": "Typography for keyboard shortcuts display"
      },
      "color": {
        "value": "{color.text.neutral.subtitle.1}",
        "type": "color",
        "description": "Text color for keyboard shortcuts"
      },
      "background": {
        "value": "{color.background.neutral.subtle.1}",
        "type": "color",
        "description": "Background color for keyboard shortcut badge"
      },
      "padding": {
        "vertical": {
          "value": "{padding.0[5]}",
          "type": "dimension",
          "description": "Vertical padding for keyboard shortcut badge"
        },
        "horizontal": {
          "value": "{padding.1}",
          "type": "dimension",
          "description": "Horizontal padding for keyboard shortcut badge"
        }
      },
      "border-radius": {
        "value": "{border.radius.xs}",
        "type": "dimension",
        "description": "Border radius for keyboard shortcut badge"
      }
    }
  }
}
